D flip flop/dFlipFlop.v
`timescale 1ns / 1ps

module d_flip_flop (
    input d,
    input clk,
    output wire q,
    output wire p
);

    wire x, y;

    assign x = ~(d & clk);
    assign y = ~((~d) & clk);

    assign q = ~(x & p);
    assign p = ~(y & q);

endmodule

buffer register/4Bit/bufferRegister4Bit.v
`timescale 1ns / 1ps
`include "../../D flip flop/dFlipFlop.v"

module buffer_register_4_bit (
    input wire [3:0] x,
    input load,
    input clk,
    output wire [3:0] q,
    output wire [3:0] p
);

    wire [3:0] d;

    assign d[0] = load ? x[0] : q[0];
    assign d[1] = load ? x[1] : q[1];
    assign d[2] = load ? x[2] : q[2];
    assign d[3] = load ? x[3] : q[3];

    d_flip_flop dff0 (.d(d[0]), .clk(clk), .q(q[0]), .p(p[0]));
    d_flip_flop dff1 (.d(d[1]), .clk(clk), .q(q[1]), .p(p[1]));
    d_flip_flop dff2 (.d(d[2]), .clk(clk), .q(q[2]), .p(p[2]));
    d_flip_flop dff3 (.d(d[3]), .clk(clk), .q(q[3]), .p(p[3]));

endmodule

clock/clock.v
`timescale 1ns/1ps

module clock (
    output reg clk1
);

    initial clk1 = 0;

    always #1 clk1 = ~clk1; // toggle every 1 time unit

endmodule

buffer register/4Bit/bufferRegister4BitTB.v
`timescale 1ns / 1ps
`include "../../clock/clock.v"

module tb_buffer_register_4_bit;

    reg [3:0] x;
    reg load;
    wire clk;
    wire [3:0] q, p;

    clock clk_gen(clk);

    buffer_register_4_bit dut (.x(x), .load(load), .clk(clk), .q(q), .p(p));

    initial begin
        $dumpfile("bufferRegister4BitTB.vcd");
        $dumpvars(0, tb_buffer_register_4_bit);
        #100 $finish;
    end

    initial begin
        $monitor("t=%0t | d=%b load=%b clk=%b q=%b p=%b", $time, x, load, clk, q, p);

        x = 4'b0001; load = 1; #20;
        
    end

endmodule

verilog/buffer register/4Bit/bufferRegister4BitTB.vcd
$date
	Tue Aug 26 11:52:44 2025
$end
$version
	Icarus Verilog
$end
$timescale
	1ps
$end
$scope module tb_buffer_register_4_bit $end
$var wire 4 ! q [3:0] $end
$var wire 4 " p [3:0] $end
$var wire 1 # clk $end
$var reg 1 $ load $end
$var reg 4 % x [3:0] $end
$scope module clk_gen $end
$var reg 1 # clk1 $end
$upscope $end
$scope module dut $end
$var wire 1 # clk $end
$var wire 1 $ load $end
$var wire 4 & x [3:0] $end
$var wire 4 ' q [3:0] $end
$var wire 4 ( p [3:0] $end
$var wire 4 ) d [3:0] $end
$scope module dff0 $end
$var wire 1 # clk $end
$var wire 1 * d $end
$var wire 1 + p $end
$var wire 1 , q $end
$var wire 1 - x $end
$var wire 1 . y $end
$upscope $end
$scope module dff1 $end
$var wire 1 # clk $end
$var wire 1 / d $end
$var wire 1 0 p $end
$var wire 1 1 q $end
$var wire 1 2 x $end
$var wire 1 3 y $end
$upscope $end
$scope module dff2 $end
$var wire 1 # clk $end
$var wire 1 4 d $end
$var wire 1 5 p $end
$var wire 1 6 q $end
$var wire 1 7 x $end
$var wire 1 8 y $end
$upscope $end
$scope module dff3 $end
$var wire 1 # clk $end
$var wire 1 9 d $end
$var wire 1 : p $end
$var wire 1 ; q $end
$var wire 1 < x $end
$var wire 1 = y $end
$upscope $end
$upscope $end
$upscope $end
$enddefinitions $end
$comment Show the parameter values. $end
$dumpall
$end
#0
$dumpvars
1=
1<
x;
x:
09
18
17
x6
x5
04
13
12
x1
x0
0/
1.
1-
x,
x+
1*
b1 )
bx (
bx '
b1 &
b1 %
1$
0#
bx "
bx !
$end
#1000
0+
01
06
0;
b1 !
b1 '
1,
10
15
b1110 "
b1110 (
1:
0-
03
08
0=
1#
#2000
1-
13
18
1=
0#
#3000
0-
03
08
0=
1#
#4000
1-
13
18
1=
0#
#5000
0-
03
08
0=
1#
#6000
1-
13
18
1=
0#
#7000
0-
03
08
0=
1#
#8000
1-
13
18
1=
0#
#9000
0-
03
08
0=
1#
#10000
1-
13
18
1=
0#
#11000
0-
03
08
0=
1#
#12000
1-
13
18
1=
0#
#13000
0-
03
08
0=
1#
#14000
1-
13
18
1=
0#
#15000
0-
03
08
0=
1#
#16000
1-
13
18
1=
0#
#17000
0-
03
08
0=
1#
#18000
1-
13
18
1=
0#
#19000
0-
03
08
0=
1#
#20000
1-
13
18
1=
0#
#21000
0-
03
08
0=
1#
#22000
1-
13
18
1=
0#
#23000
0-
03
08
0=
1#
#24000
1-
13
18
1=
0#
#25000
0-
03
08
0=
1#
#26000
1-
13
18
1=
0#
#27000
0-
03
08
0=
1#
#28000
1-
13
18
1=
0#
#29000
0-
03
08
0=
1#
#30000
1-
13
18
1=
0#
#31000
0-
03
08
0=
1#
#32000
1-
13
18
1=
0#
#33000
0-
03
08
0=
1#
#34000
1-
13
18
1=
0#
#35000
0-
03
08
0=
1#
#36000
1-
13
18
1=
0#
#37000
0-
03
08
0=
1#
#38000
1-
13
18
1=
0#
#39000
0-
03
08
0=
1#
#40000
1-
13
18
1=
0#
#41000
0-
03
08
0=
1#
#42000
1-
13
18
1=
0#
#43000
0-
03
08
0=
1#
#44000
1-
13
18
1=
0#
#45000
0-
03
08
0=
1#
#46000
1-
13
18
1=
0#
#47000
0-
03
08
0=
1#
#48000
1-
13
18
1=
0#
#49000
0-
03
08
0=
1#
#50000
1-
13
18
1=
0#
#51000
0-
03
08
0=
1#
#52000
1-
13
18
1=
0#
#53000
0-
03
08
0=
1#
#54000
1-
13
18
1=
0#
#55000
0-
03
08
0=
1#
#56000
1-
13
18
1=
0#
#57000
0-
03
08
0=
1#
#58000
1-
13
18
1=
0#
#59000
0-
03
08
0=
1#
#60000
1-
13
18
1=
0#
#61000
0-
03
08
0=
1#
#62000
1-
13
18
1=
0#
#63000
0-
03
08
0=
1#
#64000
1-
13
18
1=
0#
#65000
0-
03
08
0=
1#
#66000
1-
13
18
1=
0#
#67000
0-
03
08
0=
1#
#68000
1-
13
18
1=
0#
#69000
0-
03
08
0=
1#
#70000
1-
13
18
1=
0#
#71000
0-
03
08
0=
1#
#72000
1-
13
18
1=
0#
#73000
0-
03
08
0=
1#
#74000
1-
13
18
1=
0#
#75000
0-
03
08
0=
1#
#76000
1-
13
18
1=
0#
#77000
0-
03
08
0=
1#
#78000
1-
13
18
1=
0#
#79000
0-
03
08
0=
1#
#80000
1-
13
18
1=
0#
#81000
0-
03
08
0=
1#
#82000
1-
13
18
1=
0#
#83000
0-
03
08
0=
1#
#84000
1-
13
18
1=
0#
#85000
0-
03
08
0=
1#
#86000
1-
13
18
1=
0#
#87000
0-
03
08
0=
1#
#88000
1-
13
18
1=
0#
#89000
0-
03
08
0=
1#
#90000
1-
13
18
1=
0#
#91000
0-
03
08
0=
1#
#92000
1-
13
18
1=
0#
#93000
0-
03
08
0=
1#
#94000
1-
13
18
1=
0#
#95000
0-
03
08
0=
1#
#96000
1-
13
18
1=
0#
#97000
0-
03
08
0=
1#
#98000
1-
13
18
1=
0#
#99000
0-
03
08
0=
1#
#100000
1-
13
18
1=
0#
