verilog/d-latch/dLatch.v
`timescale 1ns / 1ps

module d_latch (
    input d,
    input clk,
    output wire q,
    output wire p
);
    wire s, r;

    assign s = (~d) & clk;
    assign r = d & clk;

    assign q = ~(s & p);
    assign p = ~(r & q);

endmodule

clock/clock.v
`timescale 1ns/1ps

module clock (
    output reg clk1
);

    initial clk1 = 0;

    always #1 clk1 = ~clk1; // toggle every 1 time unit

endmodule

d-latch/dLatchTB.v
`timescale 1ns/1ps
`include "../clock/clock.v"

module tb_d_latch;

    reg d;
    wire clk, q, p; // wire driven by clock module
    
    clock clk_gen(clk);

    d_latch uut (d, clk, q, p);

    initial begin
        $dumpfile("dLatchTB.vcd");
        $dumpvars(0, tb_d_latch);
        #100 $finish;
    end

    initial begin
        $display("test d-latch");
        $monitor("t=%0t | d=%b clk=%b q=%b p=%b", $time, d, clk, q, p);

        d = 0; #20;
        d = 1; #20;
        d = 0; #20;
        d = 1; #20;
    end

endmodule

verilog/d-latch/dLatchTB.vcd
$date
	Thu Aug 21 13:43:18 2025
$end
$version
	Icarus Verilog
$end
$timescale
	1ps
$end
$scope module tb_d_latch $end
$var wire 1 ! q $end
$var wire 1 " p $end
$var wire 1 # clk $end
$var reg 1 $ d $end
$scope module clk_gen $end
$var reg 1 # clk1 $end
$upscope $end
$scope module uut $end
$var wire 1 # clk $end
$var wire 1 $ d $end
$var wire 1 " p $end
$var wire 1 ! q $end
$var wire 1 % r $end
$var wire 1 & s $end
$upscope $end
$upscope $end
$enddefinitions $end
$comment Show the parameter values. $end
$dumpall
$end
#0
$dumpvars
0&
0%
0$
0#
1"
1!
$end
#1000
0!
1&
1#
#2000
1!
0&
0#
#3000
0!
1&
1#
#4000
1!
0&
0#
#5000
0!
1&
1#
#6000
1!
0&
0#
#7000
0!
1&
1#
#8000
1!
0&
0#
#9000
0!
1&
1#
#10000
1!
0&
0#
#11000
0!
1&
1#
#12000
1!
0&
0#
#13000
0!
1&
1#
#14000
1!
0&
0#
#15000
0!
1&
1#
#16000
1!
0&
0#
#17000
0!
1&
1#
#18000
1!
0&
0#
#19000
0!
1&
1#
#20000
1!
0&
0#
1$
#21000
0"
1%
1#
#22000
1"
0%
0#
#23000
0"
1%
1#
#24000
1"
0%
0#
#25000
0"
1%
1#
#26000
1"
0%
0#
#27000
0"
1%
1#
#28000
1"
0%
0#
#29000
0"
1%
1#
#30000
1"
0%
0#
#31000
0"
1%
1#
#32000
1"
0%
0#
#33000
0"
1%
1#
#34000
1"
0%
0#
#35000
0"
1%
1#
#36000
1"
0%
0#
#37000
0"
1%
1#
#38000
1"
0%
0#
#39000
0"
1%
1#
#40000
1"
0%
0#
0$
#41000
0!
1&
1#
#42000
1!
0&
0#
#43000
0!
1&
1#
#44000
1!
0&
0#
#45000
0!
1&
1#
#46000
1!
0&
0#
#47000
0!
1&
1#
#48000
1!
0&
0#
#49000
0!
1&
1#
#50000
1!
0&
0#
#51000
0!
1&
1#
#52000
1!
0&
0#
#53000
0!
1&
1#
#54000
1!
0&
0#
#55000
0!
1&
1#
#56000
1!
0&
0#
#57000
0!
1&
1#
#58000
1!
0&
0#
#59000
0!
1&
1#
#60000
1!
0&
0#
1$
#61000
0"
1%
1#
#62000
1"
0%
0#
#63000
0"
1%
1#
#64000
1"
0%
0#
#65000
0"
1%
1#
#66000
1"
0%
0#
#67000
0"
1%
1#
#68000
1"
0%
0#
#69000
0"
1%
1#
#70000
1"
0%
0#
#71000
0"
1%
1#
#72000
1"
0%
0#
#73000
0"
1%
1#
#74000
1"
0%
0#
#75000
0"
1%
1#
#76000
1"
0%
0#
#77000
0"
1%
1#
#78000
1"
0%
0#
#79000
0"
1%
1#
#80000
1"
0%
0#
#81000
0"
1%
1#
#82000
1"
0%
0#
#83000
0"
1%
1#
#84000
1"
0%
0#
#85000
0"
1%
1#
#86000
1"
0%
0#
#87000
0"
1%
1#
#88000
1"
0%
0#
#89000
0"
1%
1#
#90000
1"
0%
0#
#91000
0"
1%
1#
#92000
1"
0%
0#
#93000
0"
1%
1#
#94000
1"
0%
0#
#95000
0"
1%
1#
#96000
1"
0%
0#
#97000
0"
1%
1#
#98000
1"
0%
0#
#99000
0"
1%
1#
#100000
1"
0%
0#
